{
"type": "FeatureCollection",
"name": "epicentre",
"crs": { "type": "name", "properties": { "name": "urn:ogc:def:crs:OGC:1.3:CRS84" } },
"features": [
{ "type": "Feature", "properties": { "id": 1.0, "nom": "Ighli", "lmda": -8.256, "alpha": 30.9519 }, "geometry": { "type": "Point", "coordinates": [ -8.256363726524219, 30.951930911824441 ] } }
]
}
